taku/__init__.py
taku/command_parser.py
taku/exceptions.py
taku/run.py
taku_cli-0.4.14.dist-info/WHEEL
taku_cli-0.4.14.dist-info/entry_points.txt
taku_cli-0.4.14.dist-info/METADATA
taku_cli-0.4.14.dist-info/RECORD
