Metadata-Version: 2.3
Name: taku-cli
Version: 0.4.14
Summary: Simple script manager for creating, running, and syncing bash scripts
Keywords: automation,bash,cli,scripts
Author: Tobi-De
Author-email: Tobi-De <tobidegnon@proton.me>
License: MIT
Classifier: Development Status :: 4 - Beta
Classifier: Intended Audience :: Developers
Classifier: License :: OSI Approved :: MIT License
Classifier: Programming Language :: Python :: 3 :: Only
Classifier: Programming Language :: Python :: 3.12
Classifier: Programming Language :: Python :: 3.13
Classifier: Topic :: Software Development :: Build Tools
Classifier: Topic :: System :: Shells
Classifier: Topic :: Utilities
Requires-Dist: tomli-w>=1.2
Requires-Dist: rich-argparse>=1.7.1 ; extra == 'bling'
Requires-Python: >=3.12
Project-URL: Homepage, https://github.com/Tobi-De/taku
Project-URL: Issues, https://github.com/Tobi-De/taku/issues
Project-URL: Repository, https://github.com/Tobi-De/taku
Provides-Extra: bling
